cvtk/__init__.py
cvtk/__main__.py
cvtk/io/__init__.py
cvtk/io/csv.py
cvtk/io/image.py
cvtk/io/json.py
cvtk/io/utils.py
cvtk/losses/__init__.py
cvtk/losses/box_loss.py
cvtk/losses/grid_loss.py
cvtk/losses/line_loss.py
cvtk/losses/mixed_loss.py
cvtk/losses/train_segmentation_with_bbox/__init__.py
cvtk/losses/train_segmentation_with_bbox/_utils.py
cvtk/losses/train_segmentation_with_bbox/free_loss.py
cvtk/losses/train_segmentation_with_bbox/grid_loss.py
cvtk/losses/train_segmentation_with_bbox/line_loss.py
cvtk/losses/train_segmentation_with_bbox/topk_loss.py
cvtk/models/__init__.py
cvtk/models/segmentation/__init__.py
cvtk/models/segmentation/coco_utils.py
cvtk/models/segmentation/segmentation.py
cvtk/models/segmentation/utils.py
cvtk/text/__init__.py
cvtk/text/utils.py
cvtk/tools/__init__.py
cvtk/tools/__main__.py
cvtk/tools/folder.py
cvtk/tools/publish_mmdet.py
cvtk/transforms/__init__.py
cvtk/transforms/gaussian.py
cvtk/transforms/mmdet.py
cvtk/utils/__init__.py
cvtk/utils/average_checkpoints.py
cvtk/utils/notebook.py
cvtk/utils/abc/__init__.py
cvtk/utils/abc/discover.py
cvtk/utils/abc/gen.py
cvtk/utils/abc/nms.py
cvtk/utils/abc/patch.py
cvtk/utils/abc/visualize.py
cvtk/utils/abc/coco/__init__.py
cvtk/utils/abc/coco/build.py
cvtk/utils/abc/coco/image.py
cvtk/utils/abc/coco/sampling.py
cvtk/utils/abc/coco/yolo.py
cvtk/utils/data/__init__.py
cvtk/utils/plotly/__init__.py
cvtk/utils/plotly/color.py
cvtk/utils/plotly/image.py
cvtk/utils/plotly/interact.py
cvtk-0.3.21.dist-info/LICENSE
cvtk-0.3.21.dist-info/METADATA
cvtk-0.3.21.dist-info/WHEEL
cvtk-0.3.21.dist-info/top_level.txt
cvtk-0.3.21.dist-info/RECORD
