Metadata-Version: 2.1
Name: cvtk
Version: 0.3.21
Summary: computer vision toolkit of pytorch
Home-page: https://github.com/flystarhe/cvtk
Author: flystarhe
Author-email: flystarhe@qq.com
License: UNKNOWN
Keywords: computer vision,machine learning
Platform: UNKNOWN
Classifier: Programming Language :: Python :: 3
Classifier: License :: OSI Approved :: MIT License
Requires-Python: >=3.6, <4
License-File: LICENSE
Requires-Dist: albumentations (>=0.5.2)
Requires-Dist: hiplot (>=0.1.23)
Requires-Dist: lxml (==4.6.2)
Requires-Dist: networkx
Requires-Dist: numpy
Requires-Dist: opencv-python (>=4.5.3)
Requires-Dist: pandas
Requires-Dist: pillow (>=8.1.2)
Requires-Dist: requests
Requires-Dist: simplejson
Requires-Dist: scikit-image (>=0.18.1)
Requires-Dist: scikit-learn (>=0.24.1)
Requires-Dist: tqdm
